{"format":2,"version":"5.5","globals":"fe2d500c6669cd33b8ec3a5c727855e5","files":{"challenge___init___py":{"hash":"eabbdcd957391e46906215ac65c665bf","index":{"nums":[1,2,0,0,0,0,0],"html_filename":"challenge___init___py.html","relative_filename":"challenge/__init__.py"}},"challenge_api_py":{"hash":"f898b9aa8af5e656dfc484342520db86","index":{"nums":[1,8,0,2,0,0,0],"html_filename":"challenge_api_py.html","relative_filename":"challenge/api.py"}},"challenge_model_py":{"hash":"5839e2b2f42d7a9e33299f7d418d1858","index":{"nums":[1,38,0,0,0,0,0],"html_filename":"challenge_model_py.html","relative_filename":"challenge/model.py"}},"challenge_utils_py":{"hash":"a1314d243f1bd053e0f26ae64d6be90e","index":{"nums":[1,6,0,6,0,0,0],"html_filename":"challenge_utils_py.html","relative_filename":"challenge/utils.py"}}}}